nepy/__init__.py
nepy/capsule/__init__.py
nepy/capsule/capsule.py
nepy/frida/__init__.py
nepy/frida/batch.py
nepy/frida/frida.py
nepy/readers/__init__.py
nepy/readers/easyReader.py
nepy/readers/nedfReader.py
nepy/tests/__init__.py
nepy/tests/test_batch.py
nepy/tests/test_capsule.py
nepy/tests/test_data.py
nepy/tests/test_easyReader.py
nepy/tests/test_frida.py
nepy/tests/test_nedfReader.py
NEPy-1.0.dist-info/LICENSE
NEPy-1.0.dist-info/METADATA
NEPy-1.0.dist-info/WHEEL
NEPy-1.0.dist-info/top_level.txt
NEPy-1.0.dist-info/RECORD
