Metadata-Version: 1.0
Name: NEPy
Version: 1.0
Summary: python tool to read and  preprocess .easy and .nedf Neuroelectrics' EEG files
Home-page: http://wiki.neuroelectrics.com
Author: Giulio Ruffini and Roser Sanchez
Author-email: roser.sanchez@neuroelectrics.com
License: UNKNOWN
Platform: UNKNOWN
